[
  {
    "id": "cp-01:hp_pill",
    "name": "黄龙丹",
    "category": "consumable",
    "rarity": "common",
    "description": "恢复 60 HP",
    "stackable": true,
    "maxStack": 99,
    "usable": true,
    "effects": { "hp": 60 },
    "effectMessage": "💊 服下黄龙丹，气血充盈，恢复 60 HP。",
    "sellPrice": 10
  },
  {
    "id": "cp-01:mp_pill",
    "name": "清灵丹",
    "category": "consumable",
    "rarity": "common",
    "description": "恢复 35 MP",
    "stackable": true,
    "maxStack": 99,
    "usable": true,
    "effects": { "mp": 35 },
    "effectMessage": "💊 服下清灵丹，灵力回涌，恢复 35 MP。",
    "sellPrice": 10
  },
  {
    "id": "cp-01:stamina_pill",
    "name": "培元丹",
    "category": "consumable",
    "rarity": "common",
    "description": "恢复 35 精力",
    "stackable": true,
    "maxStack": 99,
    "usable": true,
    "effects": { "stamina": 35 },
    "effectMessage": "💊 服下培元丹，精神焕发，恢复 35 精力。",
    "sellPrice": 8
  },
  {
    "id": "cp-01:exp_pill",
    "name": "筑基丹",
    "category": "consumable",
    "rarity": "uncommon",
    "description": "获得 80 修为",
    "stackable": true,
    "maxStack": 99,
    "usable": true,
    "effects": { "exp": 80 },
    "effectMessage": "💊 服下筑基丹，丹力化为修为，增长 80。",
    "sellPrice": 35
  },
  {
    "id": "cp-01:jichu_pill",
    "name": "基础丹",
    "category": "consumable",
    "rarity": "common",
    "description": "获得 30 修为",
    "stackable": true,
    "maxStack": 99,
    "usable": true,
    "effects": { "exp": 30 },
    "effectMessage": "💊 服下基础丹，修为略有增长。",
    "sellPrice": 12
  },
  {
    "id": "cp-01:lianqi_pill",
    "name": "炼气丹",
    "category": "consumable",
    "rarity": "uncommon",
    "description": "获得 150 修为",
    "stackable": true,
    "maxStack": 99,
    "usable": true,
    "effects": { "exp": 150 },
    "effectMessage": "💊 服下炼气丹，灵力流转全身，修为大增。",
    "sellPrice": 50
  },
  {
    "id": "cp-01:golden_core_pill",
    "name": "结丹丹",
    "category": "consumable",
    "rarity": "rare",
    "description": "获得 500 修为",
    "stackable": true,
    "maxStack": 50,
    "usable": true,
    "effects": { "exp": 500 },
    "effectMessage": "💊 服下结丹丹，金丹之力涌入经脉，修为暴涨。",
    "sellPrice": 180
  },
  {
    "id": "cp-01:nascent_soul_pill",
    "name": "元婴丹",
    "category": "consumable",
    "rarity": "epic",
    "description": "获得 2000 修为",
    "stackable": true,
    "maxStack": 20,
    "usable": true,
    "effects": { "exp": 2000 },
    "effectMessage": "🌟 服下元婴丹，元神震荡，修为飞速提升！",
    "sellPrice": 600
  },
  {
    "id": "cp-01:mood_pill",
    "name": "宁心丹",
    "category": "consumable",
    "rarity": "common",
    "description": "心情 +25",
    "stackable": true,
    "maxStack": 99,
    "usable": true,
    "effects": { "mood": 25 },
    "effectMessage": "💊 服下宁心丹，心神安宁。",
    "sellPrice": 8
  },
  {
    "id": "cp-01:health_pill",
    "name": "驻颜丹",
    "category": "consumable",
    "rarity": "uncommon",
    "description": "健康 +30",
    "stackable": true,
    "maxStack": 99,
    "usable": true,
    "effects": { "health": 30 },
    "effectMessage": "💊 服下驻颜丹，容颜焕发，身体康健。",
    "sellPrice": 15
  },
  {
    "id": "cp-01:enlightenment_pill",
    "name": "悟道丹",
    "category": "consumable",
    "rarity": "epic",
    "description": "获得 3000 修为",
    "stackable": true,
    "maxStack": 10,
    "usable": true,
    "effects": { "exp": 3000 },
    "effectMessage": "🌟 服下悟道丹，醍醐灌顶，修为暴涨！",
    "sellPrice": 1000
  },
  {
    "id": "cp-01:longevity_pill",
    "name": "延寿丹",
    "category": "consumable",
    "rarity": "rare",
    "description": "延长寿命 50 年",
    "stackable": true,
    "maxStack": 3,
    "usable": true,
    "effects": { "lifespan": 600 },
    "effectMessage": "💊 服下延寿丹，寿限延长 50 年。",
    "sellPrice": 300
  },
  {
    "id": "cp-01:full_restore_pill",
    "name": "万灵归元丹",
    "category": "consumable",
    "rarity": "epic",
    "description": "完全恢复 HP / MP / 精力",
    "stackable": true,
    "maxStack": 10,
    "usable": true,
    "effects": { "hp": "max", "mp": "max", "stamina": "max" },
    "effectMessage": "🌟 服下万灵归元丹，全身伤势尽数恢复！",
    "sellPrice": 500
  },
  {
    "id": "cp-01:spirit_water",
    "name": "灵泉水",
    "category": "consumable",
    "rarity": "uncommon",
    "description": "恢复 25 HP + 25 MP",
    "stackable": true,
    "maxStack": 99,
    "usable": true,
    "effects": { "hp": 25, "mp": 25 },
    "effectMessage": "💧 饮下灵泉水，身心舒畅。",
    "sellPrice": 15
  },
  {
    "id": "cp-01:life_talisman",
    "name": "护身灵符",
    "category": "consumable",
    "rarity": "uncommon",
    "description": "蕴含灵力的护身符，可抵消一次致命伤害",
    "stackable": true,
    "maxStack": 5,
    "usable": false,
    "sellPrice": 80
  },
  {
    "id": "cp-01:jade_shield",
    "name": "护身玉佩",
    "category": "consumable",
    "rarity": "rare",
    "description": "碎裂护主的灵玉护佩",
    "stackable": true,
    "maxStack": 3,
    "usable": false,
    "sellPrice": 200
  },
  {
    "id": "cp-01:nine_turn_pill",
    "name": "九转回魂丹",
    "category": "consumable",
    "rarity": "legendary",
    "description": "起死回生之丹，传说中的仙丹",
    "stackable": true,
    "maxStack": 1,
    "usable": false,
    "sellPrice": 2000
  },
  {
    "id": "cp-01:calming_talisman",
    "name": "定心符",
    "category": "consumable",
    "rarity": "uncommon",
    "description": "驱散心魔的符箓",
    "stackable": true,
    "maxStack": 5,
    "usable": false,
    "sellPrice": 40
  },
  {
    "id": "cp-01:soul_lamp",
    "name": "魂灯",
    "category": "consumable",
    "rarity": "epic",
    "description": "灯火护魂，封印一缕魂火",
    "stackable": true,
    "maxStack": 1,
    "usable": false,
    "sellPrice": 500
  },
  {
    "id": "cp-01:herb_lingcao",
    "name": "灵草",
    "category": "material",
    "rarity": "common",
    "description": "基础炼丹材料，灵力温和",
    "stackable": true,
    "maxStack": 99,
    "usable": false,
    "sellPrice": 3
  },
  {
    "id": "cp-01:herb_xuanlian",
    "name": "玄莲子",
    "category": "material",
    "rarity": "uncommon",
    "description": "玄莲所结之子，中阶炼丹材料",
    "stackable": true,
    "maxStack": 99,
    "usable": false,
    "sellPrice": 18
  },
  {
    "id": "cp-01:herb_tianhuo",
    "name": "天火花",
    "category": "material",
    "rarity": "rare",
    "description": "生长于地火脉上的灵花，蕴含火灵力",
    "stackable": true,
    "maxStack": 99,
    "usable": false,
    "sellPrice": 55
  },
  {
    "id": "cp-01:herb_wanling",
    "name": "万灵果",
    "category": "material",
    "rarity": "epic",
    "description": "万年灵树所结之果，顶级炼丹材料",
    "stackable": true,
    "maxStack": 30,
    "usable": false,
    "sellPrice": 400
  },
  {
    "id": "cp-01:iron_ore",
    "name": "玄铁矿",
    "category": "material",
    "rarity": "common",
    "description": "基础炼器材料，硬度极高",
    "stackable": true,
    "maxStack": 99,
    "usable": false,
    "sellPrice": 3
  },
  {
    "id": "cp-01:mithril_ore",
    "name": "秘银矿",
    "category": "material",
    "rarity": "uncommon",
    "description": "蕴含灵力的稀有矿石",
    "stackable": true,
    "maxStack": 99,
    "usable": false,
    "sellPrice": 20
  },
  {
    "id": "cp-01:star_iron",
    "name": "星陨铁",
    "category": "material",
    "rarity": "rare",
    "description": "天外陨石中提炼的稀有金属",
    "stackable": true,
    "maxStack": 50,
    "usable": false,
    "sellPrice": 80
  },
  {
    "id": "cp-01:monster_core",
    "name": "妖丹",
    "category": "material",
    "rarity": "rare",
    "description": "妖兽体内的丹核，蕴含灵力",
    "stackable": true,
    "maxStack": 99,
    "usable": false,
    "sellPrice": 80
  },
  {
    "id": "cp-01:monster_fang",
    "name": "妖牙",
    "category": "material",
    "rarity": "common",
    "description": "妖兽牙齿，炼器辅材",
    "stackable": true,
    "maxStack": 99,
    "usable": false,
    "sellPrice": 5
  },
  {
    "id": "cp-01:spirit_stone_shard",
    "name": "灵石碎片",
    "category": "material",
    "rarity": "common",
    "description": "碎裂的灵石，积攒可换灵石",
    "stackable": true,
    "maxStack": 99,
    "usable": false,
    "sellPrice": 1
  },
  {
    "id": "cp-01:jade_slip",
    "name": "玉简",
    "category": "misc",
    "rarity": "uncommon",
    "description": "记录着前人修炼心得的玉简",
    "stackable": true,
    "maxStack": 99,
    "usable": true,
    "effects": { "exp": [20, 60] },
    "effectMessage": "📜 研读玉简上的心得，领悟颇多。",
    "sellPrice": 20
  },
  {
    "id": "cp-01:map_fragment",
    "name": "地图残片",
    "category": "misc",
    "rarity": "uncommon",
    "description": "残破的秘境地图，标注着未知之地",
    "stackable": true,
    "maxStack": 10,
    "usable": false,
    "sellPrice": 25
  },
  {
    "id": "cp-01:beast_blood",
    "name": "妖兽血",
    "category": "material",
    "rarity": "common",
    "description": "妖兽精血，炼器辅材",
    "stackable": true,
    "maxStack": 99,
    "usable": false,
    "sellPrice": 4
  },
  {
    "id": "cp-01:mountain_herb",
    "name": "山灵草",
    "category": "material",
    "rarity": "common",
    "description": "野外采集的灵草，含有野性灵力",
    "stackable": true,
    "maxStack": 99,
    "usable": false,
    "sellPrice": 3
  },
  {
    "id": "cp-01:sand_crystal",
    "name": "流沙晶",
    "category": "material",
    "rarity": "uncommon",
    "description": "沙漠深处蕴育的天然晶石",
    "stackable": true,
    "maxStack": 99,
    "usable": false,
    "sellPrice": 25
  },
  {
    "id": "cp-01:mystery_fragment",
    "name": "秘境碎片",
    "category": "material",
    "rarity": "rare",
    "description": "秘境中残留的神秘物质，蕴含空间法则",
    "stackable": true,
    "maxStack": 50,
    "usable": false,
    "sellPrice": 80
  },
  {
    "id": "cp-01:celestial_jade",
    "name": "仙玉",
    "category": "material",
    "rarity": "epic",
    "description": "灵界特产的高阶仙玉，灵力充沛",
    "stackable": true,
    "maxStack": 30,
    "usable": false,
    "sellPrice": 400
  },
  {
    "id": "cp-01:spirit_jade",
    "name": "灵玉",
    "category": "material",
    "rarity": "rare",
    "description": "蕴含灵力的天然玉石",
    "stackable": true,
    "maxStack": 50,
    "usable": false,
    "sellPrice": 60
  },
  {
    "id": "cp-01:golden_thunder_bamboo_leaf",
    "name": "金雷竹叶",
    "category": "material",
    "rarity": "epic",
    "description": "金雷竹所落之叶，蕴含雷灵之力",
    "stackable": true,
    "maxStack": 20,
    "usable": false,
    "sellPrice": 350
  },
  {
    "id": "cp-01:qingyuan_herb",
    "name": "青元草",
    "category": "material",
    "rarity": "uncommon",
    "description": "黄枫谷特产灵草，温养经脉",
    "stackable": true,
    "maxStack": 99,
    "usable": false,
    "sellPrice": 15
  },
  {
    "id": "cp-01:ice_silkworm_thread",
    "name": "冰蚕丝",
    "category": "material",
    "rarity": "rare",
    "description": "极寒灵虫所产，韧性极强",
    "stackable": true,
    "maxStack": 50,
    "usable": false,
    "sellPrice": 70
  },
  {
    "id": "cp-01:qixuan_token",
    "name": "七玄门令牌",
    "category": "misc",
    "rarity": "uncommon",
    "description": "七玄门弟子身份令牌",
    "stackable": false,
    "maxStack": 1,
    "usable": false,
    "sellPrice": 25
  },
  {
    "id": "cp-01:luanxing_chart",
    "name": "乱星海航图",
    "category": "misc",
    "rarity": "rare",
    "description": "标注了乱星海各岛屿位置的航图",
    "stackable": false,
    "maxStack": 1,
    "usable": false,
    "sellPrice": 100
  },
  {
    "id": "cp-01:breakthrough_lianqi",
    "name": "引气散",
    "category": "consumable",
    "rarity": "common",
    "description": "引气入体的散剂，突破炼气期必需",
    "stackable": true,
    "maxStack": 10,
    "usable": false,
    "sellPrice": 5
  },
  {
    "id": "cp-01:foundation_pill",
    "name": "筑基丹（突破）",
    "category": "consumable",
    "rarity": "uncommon",
    "description": "凝聚筑基所需的丹药",
    "stackable": true,
    "maxStack": 10,
    "usable": false,
    "sellPrice": 30
  },
  {
    "id": "cp-01:core_formation_stone",
    "name": "结丹凝结石",
    "category": "material",
    "rarity": "rare",
    "description": "蕴含天地精华的奇石，助结丹成形",
    "stackable": true,
    "maxStack": 10,
    "usable": false,
    "sellPrice": 100
  },
  {
    "id": "cp-01:nascent_soul_formation_pill",
    "name": "元婴化形丹",
    "category": "consumable",
    "rarity": "rare",
    "description": "引导元婴化形的珍贵丹药",
    "stackable": true,
    "maxStack": 5,
    "usable": false,
    "sellPrice": 200
  },
  {
    "id": "cp-01:deity_transform_dew",
    "name": "化神仙露",
    "category": "consumable",
    "rarity": "epic",
    "description": "传说中的仙露，可助化神突破",
    "stackable": true,
    "maxStack": 3,
    "usable": false,
    "sellPrice": 500
  },
  {
    "id": "cp-01:integration_pill",
    "name": "合体灵丹",
    "category": "consumable",
    "rarity": "epic",
    "description": "合体期突破所需的珍贵灵丹",
    "stackable": true,
    "maxStack": 3,
    "usable": false,
    "sellPrice": 600
  },
  {
    "id": "cp-01:mahayana_scroll",
    "name": "大乘心法残卷",
    "category": "material",
    "rarity": "legendary",
    "description": "记载大乘奥义的残卷",
    "stackable": true,
    "maxStack": 5,
    "usable": false,
    "sellPrice": 1000
  }
]
